{"ModuleCode":"AR5958","ModuleTitle":"Topics in Urbanism","Department":"Architecture","ModuleDescription":"This module will involve a critical and thorough discussion\nof specific topics in Urban Studies, including Urban Design\nand Planning. Examples of topics that may be studied are:\nTropical Urban Design, Sustainable Urban Design,\nEcourbansim, Urban Design methodologies and practice.","ModuleCredit":"4","Workload":"0-2-0-2-6","History":[{"Semester":2,"LecturePeriods":["Wednesday Morning"]}]}