{"ModuleCode":"BMF5323","ModuleTitle":"Accounting for Finance Professionals","Department":"Dean's Office (Biz)","ModuleDescription":"The course stresses the theory of accounts, generally\naccepted accounting principles, and the interpretation of\nfinancial statements. The perspective of the course is that\nof managers and investors as knowledgeable users of\naccounting information.","ModuleCredit":"2","Workload":"1-0.5-0-0-3.5","History":[{"Semester":1,"LecturePeriods":["Tuesday Afternoon","Thursday Afternoon"]}]}