{"ModuleCode":"BPM1705","ModuleTitle":"Understanding How Business Works","Department":"Marketing","ModuleDescription":"This module introduces new students to the nuts and bolts of the business functions of finance, human resource management, marketing and operations management. It allows students to have insights into how these functional areas work together for a business to function and grow. This module will take students through the journey of a new business from business idea conception to funding and commercialization.","ModuleCredit":"0","Workload":"0-3-0-3-4","Types":["Module"],"History":[{"Semester":1,"LecturePeriods":["Saturday Morning","Saturday Afternoon"]}]}