{"ModuleCode":"ECA5334","ModuleTitle":"Corporate Finance","Department":"Economics","ModuleDescription":"This module provides a theoretical and practical treatment of corporate financial theory for students who have completed an introductory course in financial economics. Topics covered in this course will include: an overview of financial management; comparisons of financial and real investment; capital budgeting and valuing real assets and real options; risk and return of assets; capital structure and dividend policy, and mergers and acquisitions; applications of portfolio management techniques in corporate finance.","ModuleCredit":"4","Workload":"2-1-0-2-5","Prerequisite":"EC5274/EC5333/ECA5333","Preclusion":"EC5269/EC5334","Corequisite":"NIL","History":[{"Semester":1,"ExamDate":"2018-12-03T09:00+0800","LecturePeriods":["Monday Evening"]}]}