{"ModuleCode":"EE6438","ModuleTitle":"Magnetic materials and devices","Department":"Electrical & Computer Engineering","ModuleDescription":"The main objective of this course is to introduce students to the basic concepts of magnetism, magnetic materials and devices and related applications in data storage from the electrical engineering perspective. As this module is intended to help students who are doing research in relevant areas to master both theoretical knowledge and practical techniques in areas of magnetism and magnetic materials, a significant portion of this module will be devoted to the coverage of various types of characterization techniques of magnetic materials. Apart from attending lectures, students will also have to do a presentation on selected topics relevant to contents covered in this module.","ModuleCredit":"4","Workload":"3-0-0-3-4","Prerequisite":"EE5431/EE5431R or EE5433R","History":[{"Semester":1,"ExamDate":"2018-11-30T09:00+0800","LecturePeriods":["Tuesday Evening"]}]}