{"ModuleCode":"IE5001","ModuleTitle":"Operations Planning And Control I","Department":"Industrial Systems Engineering & Mgt","ModuleDescription":"Operations research and its applications, mainly in the area of production planning and control: linear programming, network analysis, project planning and scheduling, dynamic programming, inventory control models, queueing theory, replacement theory and maintenance models.","ModuleCredit":"4","Workload":"3-0-0-3-4","Preclusion":"BDC5101 Deterministic Operations Research Models","History":[{"Semester":1,"ExamDate":"2018-11-28T17:00+0800","LecturePeriods":["Friday Evening"]}]}