{"ModuleCode":"IS4100","ModuleTitle":"IT Project Management","Department":"Information Systems & Analytics","ModuleDescription":"This module focuses on the management of IS projects. Various managerial issues pertaining to the evaluation and selection of information systems projects, choice of project organization, planning, scheduling and budgeting of project activities and basic principles in control and project auditing will be covered. The students will also learn how to use practical techniques and tools, such as network models (PERT/CPM), simulation, and state-of-the-art project management software, in scheduling project activities. This module serves as a good introduction to information systems project management for students who may participate in coordinating and managing large-scale information systems projects.","ModuleCredit":"4","Workload":"2-1-0-3-4","Prerequisite":"IS2102 and IS2103 and [(IS1103 or equivalent) or EG2401]","Preclusion":"IS5110 and CS5212(old code for IS5110)","Types":["Module"],"History":[{"Semester":1,"LecturePeriods":["Thursday Morning"],"TutorialPeriods":["Wednesday Morning","Tuesday Afternoon"]},{"Semester":2,"LecturePeriods":["Thursday Morning"],"TutorialPeriods":["Friday Morning","Thursday Afternoon","Wednesday Afternoon"]}]}