{"ModuleCode":"JS2225","ModuleTitle":"Marketing and Consumer Culture in Japan","Department":"Japanese Studies","ModuleDescription":"Today's Japan is one of the most highly developed consumer markets. For its people shopping has presumably become the most important leisure and social activity and companies try to attract customers with continuous product and sales innovations. The module investigates this intricate relationship between business and consumer, economics and society, by looking at various case studies, for each critically identifying and discussing patterns of consumption and marketing from a multidisciplinary perspective. These case studies may include department stores, vending machines, electronic gadgets, branded merchandise, food, gift giving, and fashion goods.","ModuleCredit":"4","Workload":"2-1-0-3-4","Types":["UEM"],"History":[{"Semester":1,"ExamDate":"2018-11-29T09:00+0800","LecturePeriods":["Wednesday Afternoon"],"TutorialPeriods":["Wednesday Morning"]}]}