{"ModuleCode":"LAC3202","ModuleTitle":"Chinese 4","Department":"Centre For Language Studies","ModuleDescription":"This module is a continuation of Chinese 3 (LAC3201). Based on the 600 Chinese characters they have already learned from Chinese 1 to 3, students will be taught another 300 new characters and phrases at this stage. New words, phrases and idioms will be strengthening for the usage of the language. Short stories and articles will be used in the teaching of this module. The students will also be trained in listening to broadcast materials, speech skills as well as short essay writing.","ModuleCredit":"4","Workload":"4-0-0-2-4","Prerequisite":"Passed LAC3201 or placement test.","Preclusion":"Nil","Types":["UEM"],"History":[{"Semester":1,"LecturePeriods":["Wednesday Afternoon","Friday Afternoon"]},{"Semester":2,"LecturePeriods":["Wednesday Morning","Friday Morning"]}]}