{"ModuleCode":"MA5243","ModuleTitle":"Advanced Mathematical Programming","Department":"Mathematics","ModuleDescription":"This module is designed for graduate students in mathematics. It covers the following major topics: Introduction to convex analysis; Theory of constrained optimization; Lagrangian duality; Algorithms for constrained optimization, in particular, penalty, barrier and augmented Lagrangian methods; Interior-point methods for convex programming, in particular, linear and semidefinite programming.","ModuleCredit":"4","Workload":"3-0-0-0-7","Prerequisite":"MA3236 or departmental approval","Types":["Module"],"History":[{"Semester":1,"ExamDate":"2018-11-26T17:00+0800","LecturePeriods":["Tuesday Afternoon","Friday Morning"]}]}