{"ModuleCode":"NUR2113","ModuleTitle":"Mental Health Nursing","Department":"Nursing/Alice Lee Ctr For Nursing Stud","ModuleDescription":"This module focuses on developing students’ knowledge and skills in providing nursing care to patients with mental illnesses in both institutional and community settings. The module contents were updated according to the latest release of the diagnostic statistical manual – 5 classifications.","ModuleCredit":"4","Workload":"1-2-0-2-5","Prerequisite":"NUR1116 Psychology for Health Professionals","Corequisite":"Nil","Types":["Module"],"History":[{"Semester":1,"ExamDate":"2018-12-04T13:00+0800","LecturePeriods":["Monday Afternoon"],"TutorialPeriods":["Friday Afternoon","Wednesday Afternoon","Tuesday Morning","Wednesday Morning","Tuesday Afternoon"]}]}