{"ModuleCode":"PF2305","ModuleTitle":"Event Management","Department":"Building","ModuleDescription":"This module covers aspects of event management in the context of project and facilities management. Major topics include event context, event planning, operation and evaluation, event risk management, event sponsorship, and case studies on the management of different types of events.","ModuleCredit":"4","Workload":"2-2-0-6-0","Preclusion":"PF4307, PFM students from AY2017/18 intake and before","Types":["Module"],"History":[{"Semester":1,"ExamDate":"2018-12-03T17:00+0800","LecturePeriods":["Tuesday Afternoon"],"TutorialPeriods":["Monday Afternoon","Tuesday Afternoon"]}]}