{"ModuleCode":"PF3501","ModuleTitle":"Intelligent Facilities","Department":"Building","ModuleDescription":"Intelligent facilities are hallmarks of modern cities; they are designed and operated to help to enhance the quality of living and work. The module explores the concept of intelligence of facilities from various perspectives, and covers how a pragmatic approach can be adopted in translating the desirable features into reality in facilities through technology. Smart technologies, sensor technologies, building control and automation systems, and human-systems relationships are explored. Case studies constitute an integral part of the module. Students are recommended to take PF2503 M&E Engineering Systems before taking this module.","ModuleCredit":"4","Workload":"2-1-0-4-3","History":[{"Semester":2,"ExamDate":"2019-04-29T09:00+0800","LecturePeriods":["Thursday Afternoon"],"TutorialPeriods":["Tuesday Morning","Thursday Afternoon"]}]}