{"ModuleCode":"PL3281","ModuleTitle":"Lab in Cognitive Psychology","Department":"Psychology","ModuleDescription":"Students will be introduced to the different methodologies used in cognitive research such as classical psychophysics, signal detection theory, reaction time paradigms, judgment tasks, similarity ratings, memory measures, and psycholinguistic methods. Selected topics on perception, attention, memory, categorisation, language, problem solving, and decision making will be used to illustrate these methods. Students will work in small groups to design and conduct an experiment using these methodologies and submit individual research reports. Prior background and interest in cognitive psychology will be very helpful.","ModuleCredit":"4","Workload":"0-0-3-4-3","Prerequisite":"PL1101E, PL2131, PL2132 and PL3233","Types":["Module"],"History":[{"Semester":1,"LecturePeriods":["Monday Morning","Monday Afternoon"]}]}