{"ModuleCode":"PL3231","ModuleTitle":"Independent Research Project","Department":"Psychology","ModuleDescription":"This module allows students to undertake an individual research project under staff supervision. Students wishing to take this module are advised to obtain additional details from the Department.","ModuleCredit":"4","Workload":"0-0-0-10-0","Prerequisite":"PL1101E, PL2131, PL2132 and consent of Supervisor. Students must have at least a &quot;C&quot; grade in one of the prerequisites.","Preclusion":"NIL","Types":["Module"],"History":[{"Semester":1},{"Semester":2}]}