{"ModuleCode":"PL6883","ModuleTitle":"Selected Topics in Cognitive Psychology","Department":"Psychology","ModuleDescription":"This module is designed to cover selected topics in cognitive psychology, which include, but are not limited to, attention, perception, memory, language, consciousness, reasoning, problem-solving, judgement, and decision-making. The topic(s) to be covered in any particular year that the module is offered will depend on student demand, faculty expertise, and faculty availability. This module will follow a seminar format, requiring high levels of student participation, writing-intensive assignments, and analytic skills.","ModuleCredit":"4","Workload":"0-3-0-5-2","Prerequisite":"Admission to the NUS psychology graduate program or approval by the lecturer","History":[{"Semester":1,"LecturePeriods":["Monday Afternoon"]}]}