{"ModuleCode":"PLC5005","ModuleTitle":"Child Psychopathology","Department":"Psychology","ModuleDescription":"This module offers an advanced critical understanding of various theories of aetiology and maintenance of disorders of childhood and adolescence. Students will also acquire an understanding in the appropriate use of diagnostic classification systems and critical appraisal of such systems. The module has a strong emphasis on linking theory to applied clinical practice.","ModuleCredit":"4","Workload":"0-3-0-2-5","Prerequisite":"PLC5002 Introduction to Psychological Disorders","Preclusion":"Nil","Corequisite":"NIL","History":[{"Semester":1,"ExamDate":"2018-11-27T09:00+0800","LecturePeriods":["Wednesday Morning"]}]}