{"ModuleCode":"PR5230","ModuleTitle":"Pharmacoeconomics and Outcomes Research","Department":"Pharmacy","ModuleDescription":"This module is designed to help students develop skills to interpret and evaluate pharmacoeconomics and quality-of-life literature and use this information to make pharmaceutical products and health service decisions.","ModuleCredit":"4","Workload":"3-1-0-1-5","Prerequisite":"Acceptance in the PharmD programme or by permission","History":[{"Semester":2,"ExamDate":"2019-05-06T09:00+0800","LecturePeriods":["Wednesday Evening"]}]}