{"ModuleCode":"RE1705","ModuleTitle":"Real Estate Finance and Accounting","Department":"Real Estate","ModuleDescription":"This module equips students with the basic financial skills and knowledge necessary for further studies in real estate finance and investment track. The topics include an introduction to financial markets and financial institutions; understanding various interest rates; risks and returns; capital budgeting; accounting and financial statement analyses; financial securities; and shareholder and capital structures. Students will also have spreadsheet laboratory sessions to develop quantitative data processing skills.","ModuleCredit":"4","Workload":"2-1-1-2-4","Preclusion":"RE1101 Fundamentals of RE Finance Students from Business School and those doing a Business Minor","History":[{"Semester":2,"ExamDate":"2019-04-30T13:00+0800","LecturePeriods":["Monday Morning"],"TutorialPeriods":["Tuesday Morning","Tuesday Afternoon","Monday Afternoon"]}]}